gunicorn_environmentconfig/__init__.py
gunicorn_environmentconfig/test/__init__.py
gunicorn_environmentconfig/test/test_config.py
gunicorn_environmentconfig-1.0.1.dist-info/METADATA
gunicorn_environmentconfig-1.0.1.dist-info/WHEEL
gunicorn_environmentconfig-1.0.1.dist-info/licenses/LICENSE
gunicorn_environmentconfig-1.0.1.dist-info/RECORD
