Metadata-Version: 2.1
Name: gunicorn_environmentconfig
Version: 1.0.1
Summary: Configure gunicorn completely via environment variables
Project-URL: repository, https://github.com/ZeitOnline/gunicorn_environmentconfig
Author-email: Zeit Online <zon-backend@zeit.de>
License: BSD-3-Clause
License-File: LICENSE
Requires-Python: >=3.7
Provides-Extra: test
Requires-Dist: pytest; extra == 'test'
